yunta/__init__.py
yunta/cli.py
yunta/dca.py
yunta/dca_torch.py
yunta/interaction_utils.py
yunta/io.py
yunta/modelling.py
yunta/plots.py
yunta/scoring.py
yunta/screening.py
yunta/weights.py
yunta/data/20250409_hpi.csv
yunta/src_speedppi/alphafold/__init__.py
yunta/src_speedppi/alphafold/confidence.py
yunta/src_speedppi/alphafold/protein.py
yunta/src_speedppi/alphafold/residue_constants.py
yunta/src_speedppi/alphafold/common/__init__.py
yunta/src_speedppi/alphafold/data/__init__.py
yunta/src_speedppi/alphafold/data/foldonly.py
yunta/src_speedppi/alphafold/data/mmcif_parsing.py
yunta/src_speedppi/alphafold/data/msaonly.py
yunta/src_speedppi/alphafold/data/pair_msas.py
yunta/src_speedppi/alphafold/data/parsers.py
yunta/src_speedppi/alphafold/data/pipeline.py
yunta/src_speedppi/alphafold/data/templates.py
yunta/src_speedppi/alphafold/data/tools/__init__.py
yunta/src_speedppi/alphafold/data/tools/hhblits.py
yunta/src_speedppi/alphafold/data/tools/hhsearch.py
yunta/src_speedppi/alphafold/data/tools/hmmbuild.py
yunta/src_speedppi/alphafold/data/tools/hmmsearch.py
yunta/src_speedppi/alphafold/data/tools/jackhmmer.py
yunta/src_speedppi/alphafold/data/tools/kalign.py
yunta/src_speedppi/alphafold/data/tools/utils.py
yunta/src_speedppi/alphafold/model/__init__.py
yunta/src_speedppi/alphafold/model/all_atom.py
yunta/src_speedppi/alphafold/model/all_atom_test.py
yunta/src_speedppi/alphafold/model/common_modules.py
yunta/src_speedppi/alphafold/model/config.py
yunta/src_speedppi/alphafold/model/data.py
yunta/src_speedppi/alphafold/model/features.py
yunta/src_speedppi/alphafold/model/folding.py
yunta/src_speedppi/alphafold/model/layer_stack.py
yunta/src_speedppi/alphafold/model/layer_stack_test.py
yunta/src_speedppi/alphafold/model/lddt.py
yunta/src_speedppi/alphafold/model/lddt_test.py
yunta/src_speedppi/alphafold/model/mapping.py
yunta/src_speedppi/alphafold/model/model.py
yunta/src_speedppi/alphafold/model/modules.py
yunta/src_speedppi/alphafold/model/prng.py
yunta-0.0.6.post2.dist-info/licenses/LICENSE
yunta-0.0.6.post2.dist-info/METADATA
yunta-0.0.6.post2.dist-info/WHEEL
yunta-0.0.6.post2.dist-info/entry_points.txt
yunta-0.0.6.post2.dist-info/top_level.txt
yunta-0.0.6.post2.dist-info/RECORD
