Metadata-Version: 2.4
Name: yunta
Version: 0.0.6.post2
Summary: Predicting protein-protein interactions and structures from multiple sequence alignments.
Author-email: Eachan Johnson <eachan.johnson@crick.ac.uk>
License: Attribution-NonCommercial-ShareAlike 4.0 International
Project-URL: Homepage, https://github.com/scbirlab/yunta
Project-URL: Bug Tracker, https://github.com/scbirlab/yunta/issues
Keywords: science,biology,systems biology,biochemistry,machine learning,analysis,deep learning,alphafold2,rosettafold
Classifier: Development Status :: 3 - Alpha
Classifier: Intended Audience :: Science/Research
Classifier: Topic :: Scientific/Engineering :: Bio-Informatics
Classifier: License :: OSI Approved :: MIT License
Classifier: Programming Language :: Python :: 3.9
Classifier: Programming Language :: Python :: 3.10
Classifier: Programming Language :: Python :: 3.11
Classifier: Programming Language :: Python :: 3.12
Classifier: Programming Language :: Python :: 3 :: Only
Requires-Python: >=3.8
License-File: LICENSE
Requires-Dist: absl-py
Requires-Dist: bioino
Requires-Dist: biopython
Requires-Dist: carabiner-tools[mpl,pd]>=0.0.4
Requires-Dist: dm-haiku==0.0.12
Requires-Dist: dm-tree
Requires-Dist: jax<=0.4.35
Requires-Dist: ml-collections==0.1.0
Requires-Dist: openpyxl==3.1.0
Requires-Dist: rf2t-micro
Requires-Dist: requests
Requires-Dist: tensorflow==2.17
Requires-Dist: tensorrt
Requires-Dist: torch>=2.3
Requires-Dist: torchvision
Requires-Dist: tqdm
Provides-Extra: cuda12
Requires-Dist: jax[cuda12]<=0.4.35; extra == "cuda12"
Provides-Extra: cuda12-local
Requires-Dist: jax[cuda12_local]<=0.4.35; extra == "cuda12-local"
Provides-Extra: cuda11
Requires-Dist: jax[cuda11]<=0.4.35; extra == "cuda11"
Dynamic: license-file
